baconator/__init__.py
baconator/baconator.py
baconator/names.py
baconator-0.2.0.dist-info/LICENSE
baconator-0.2.0.dist-info/METADATA
baconator-0.2.0.dist-info/WHEEL
baconator-0.2.0.dist-info/entry_points.txt
baconator-0.2.0.dist-info/top_level.txt
baconator-0.2.0.dist-info/RECORD
