Metadata-Version: 2.1
Name: baconator
Version: 0.2.0
Summary: Hollywood-themed random name generator
Home-page: https://github.com/eladkehat/baconator
Author: Elad Kehat
Author-email: eladkehat@gmail.com
License: MIT
Keywords: haikunator heroku naming
Platform: UNKNOWN
Classifier: Development Status :: 3 - Alpha
Classifier: Intended Audience :: Developers
Classifier: License :: OSI Approved :: MIT License
Classifier: Operating System :: OS Independent
Classifier: Programming Language :: Python :: 3.7
Classifier: Topic :: Software Development
Classifier: Topic :: Utilities
Classifier: Typing :: Typed
Requires-Python: >=3.7
